gbx/__init__.py
gbx-0.0.2.dist-info/LICENSE
gbx-0.0.2.dist-info/METADATA
gbx-0.0.2.dist-info/WHEEL
gbx-0.0.2.dist-info/entry_points.txt
gbx-0.0.2.dist-info/RECORD
